{
  "2018-01-31": [
    {
      "headline": "CEO Paul Raines Resigns Due To Medical Issues",
      "description": "<img src=\"/img/CEO-Paul_Raines.jpg\" class=\"headshot\" width=\"1024\" height=\"934\" loading=\"lazy\">Mr. Raines' previously successful battle with cancer has had a recurrence requiring immediate medical treatment.",
      "source": [
        "https://www.dallasnews.com/business/retail/2018/02/05/gamestop-ceo-paul-raines-resigns-from-board-due-to-illness/"
      ],
      "icon": "fas fa-hiking",
      "tags": [
        "board-of-directors",
        "resignation",
        "CEO"
      ],
      "hidden": false
    }
  ],
  "2018-02-06": [
    {
      "headline": "New CEO Michael K. Mauler Appointed",
      "description": "<img src=\"/img/CEO-Michael_Mauler.jpg\" class=\"headshot\" width=\"200\" height=\"300\" loading=\"lazy\">Mr. Mauler, 56, has been with the Company for more than 16 years. He previously served as Executive VP and President of International, which consists of nearly 2,000 retail stores operating under the GameStop, EB Games, Micromania and Zing Pop Culture brands",
      "source": "https://news.gamestop.com/news-releases/news-release-details/gamestop-names-michael-k-mauler-its-new-chief-executive-officer",
      "icon": "fas fa-user-tie",
      "tags": [
        "board-of-directors",
        "appointment",
        "CEO"
      ],
      "hidden": false
    }
  ],
  "2018-02-14": [
    {
      "headline": "Melvin Capital Files 13F Revealing 10,016 $GME Put Contracts",
      "description": "Reporting up until 12/31/2017. The 10,016 put contracts were worth ~$18M",
      "source": "https://www.sec.gov/Archives/edgar/data/0001628110/000117266118000556/0001172661-18-000556-index.html",
      "icon": "fas fa-toilet",
      "tags": [
        "SEC",
        "filing",
        "Melvin-Capital"
      ],
      "hidden": false
    }
  ],
  "2018-02-21": [
    {
      "headline": "GME Quarterly Dividend",
      "description": "The Board declared a quarterly cash dividend of $0.38 per common share payable on March 20, 2018 to shareholders of record as of the close of business on March 5, 2018",
      "source": "https://news.gamestop.com/news-releases/news-release-details/gamestop-declares-quarterly-cash-dividend",
      "icon": "fas fa-hand-holding-usd",
      "tags": "dividend",
      "hidden": false
    }
  ],
  "2018-03-04": [
    {
      "headline": "Former GameStop CEO Paul Rains Passes Away",
      "description": "<img src=\"/img/CEO-Paul_Raines.jpg\" class=\"headshot\" width=\"1024\" height=\"934\" loading=\"lazy\">After having a brain tumor removed in 2014 with good prognosis, he had a recurrence which ultimately took his life.",
      "source": [
        "https://news.gamestop.com/news-releases/news-release-details/statement-mike-mauler-gamestop-ceo",
        "https://www.dallasnews.com/business/retail/2018/03/05/former-gamestop-ceo-paul-raines-known-for-his-personable-leadership-style-dies-at-53/",
        "https://en.wikipedia.org/wiki/J._Paul_Raines"
      ],
      "icon": "fas fa-skull-crossbones",
      "tags": [
        "resignation",
        "CEO"
      ],
      "hidden": false
    }
  ],
  "2018-03-28": [
    {
      "headline": "GameStop Reports Q2 2018 Results",
      "description": "GameStop annual income down by $300m due to fourth quarter \"asset impairment.\" Sales up 7.2 per cent to $9.2B with net income of $34.7m",
      "source": "https://news.gamestop.com/news-releases/news-release-details/gamestop-reports-sales-and-earnings-fourth-quarter-and-fiscal",
      "icon": "far fa-newspaper",
      "tags": "earnings",
      "hidden": false
    }
  ],
  "2018-05-11": [
    {
      "headline": "CEO Michael Mauler Resigns",
      "description": "<img src=\"/img/CEO-Michael_Mauler.jpg\" class=\"headshot\" width=\"200\" height=\"300\" loading=\"lazy\">The sudden and immediate replacement of the 3mo old CEO without explanation was a sign of turmoil and instability within the company. Mr. Mauler did not take any severance package or separation benefits.",
      "source": [
        "https://news.gamestop.com/news-releases/news-release-details/gamestop-announces-appointment-daniel-dematteo-interim-chief",
        "https://comicbook.com/gaming/news/gamestop-ceo-michael-mauler-resigns/"
      ],
      "icon": "fas fa-hiking",
      "tags": [
        "resignation",
        "CEO"
      ],
      "hidden": false
    },
    {
      "headline": "New Interim CEO Daniel A. DeMatteo Appointed",
      "description": "<img src=\"/img/founder-Daniel_DeMatteo.jpg\" class=\"headshot\" width=\"1175\" height=\"1762\" loading=\"lazy\">Mr. DeMatteo, one of the company's co-founders, will continue to serve as executive chairman and director. In the past, Mr. DeMatteo has served as the company's CEO and in a variety of board and executive roles since November 1996",
      "source": "https://news.gamestop.com/news-releases/news-release-details/gamestop-announces-appointment-daniel-dematteo-interim-chief",
      "icon": "fas fa-user-tie",
      "tags": [
        "appointment",
        "CEO"
      ],
      "hidden": false
    }
  ],
  "2018-05-15": [
    {
      "headline": "Melvin Capital Files 13F Revealing 11,731 $GME Put Contracts",
      "description": "Reporting up until 03/31/2018. The 11,731 put contracts were worth ~$14.8M",
      "source": "https://www.sec.gov/Archives/edgar/data/0001628110/000117266118001139/0001172661-18-001139-index.html",
      "icon": "fas fa-toilet",
      "tags": [
        "SEC",
        "filing",
        "Melvin-Capital"
      ],
      "hidden": false
    }
  ],
  "2018-05-30": [
    {
      "headline": "PayPal Study Names GameStop Top Physical Retailer",
      "description": "Steam is a popular storefront among Millennials globally (31%), the study found, while 45% of U.S. respondents picked GameStop as their favorite. Physical, established retailers are still revered by a significant amount of people despite the growth of digital gaming, Paypal said. This indicates that gamers still enjoy physical copies of their games in addition to newer download options.",
      "source": [
        "https://www.paypal.com/stories/us/paypal-2018-gaming-insights-the-gender-divide-esports-and-more",
        "https://variety.com/2018/gaming/news/paypal-superdata-streamer-study-1202825734/"
      ],
      "icon": "far fa-newspaper",
      "tags": "news",
      "hidden": false
    }
  ],
  "2018-05-31": [
    {
      "headline": "GameStop Reports Q1 2018 Earnings",
      "description": "GameStop's total global sales decreased 5.5% overall to $1.93B. This is despite the results of a recent PayPal poll, in which 45% of U.S. respondents named GameStop as their favorite retailer for purchasing video games.",
      "source": [
        "https://news.gamestop.com/news-releases/news-release-details/gamestop-reports-first-quarter-fiscal-2018-results",
        "https://seekingalpha.com/article/4178738-gamestop-corp-gme-ceo-shane-kim-on-q1-2018-results-earnings-call-transcript"
      ],
      "icon": "far fa-newspaper",
      "tags": "earnings",
      "hidden": false
    },
    {
      "headline": "New Interim CEO Shane Kim Appointed",
      "description": "<img src=\"/img/CEO-Shane_Kim.jfif\" class=\"headshot\" width=\"360\" height=\"360\" loading=\"lazy\">Kim will be the company's fourth CEO since the late J. Paul Raines left the position in November 2017, after overseeing the retailer for eight years. Kim was general manager of Microsoft Game Studios and corporate vice president for Microsoft's Interactive Entertainment Business before leaving the company in 2010. Since 2011, Kim has been a member of GameStop's board of directors.",
      "source": [
        "https://news.gamestop.com/news-releases/news-release-details/gamestop-reports-first-quarter-fiscal-2018-results",
        "https://variety.com/2018/gaming/news/shane-kim-gamestop-1202827969/"
      ],
      "icon": "fas fa-user-tie",
      "tags": [
        "appointment",
        "CEO"
      ],
      "hidden": false
    }
  ],
  "2018-06-18": [
    {
      "headline": "GameStop Looking To Be Acquired",
      "description": "GameStop was in &quot;exploratory discussions&quot; with third parties regarding a potential deal. GameStop had struggled with leadership, while its core business has faced declining sales for the past several years as more people download games directly to consoles, computers and mobile devices.\r\nIn May, GameStop named Shane Kim, a member of its board since 2011 and a former exec at Microsoft, as interim chief executive. Former CEO Michael Mauler left the post in May after only three months. Days after naming Mr. Mauler as CEO in February, the company fired its COO and its executive VP of strategic business and brand development.",
      "source": [
        "https://news.gamestop.com/news-releases/news-release-details/gamestop-confirms-exploratory-discussions-third-parties",
        "https://www.reuters.com/article/us-gamestop-m-a-exclusive-idUSKBN1JE2JI",
        "https://www.wsj.com/articles/gamestop-in-talks-about-potential-deal-1529412223",
        "https://www.bizjournals.com/newyork/news/2018/06/19/gamestop-is-for-sale-and-sycamore-is-a-likely.html"
      ],
      "icon": "far fa-object-group",
      "tags": "acquisitions",
      "hidden": false
    }
  ],
  "2018-08-14": [
    {
      "headline": "Melvin Capital Files 13F Revealing 13,281 $GME Put Contracts",
      "description": "Reporting up until 06/30/2018. The 13,281 put contracts were worth ~$19.35M",
      "source": "https://www.sec.gov/Archives/edgar/data/0001628110/000117266118001569/0001172661-18-001569-index.html",
      "icon": "fas fa-toilet",
      "tags": [
        "SEC",
        "filing",
        "Melvin-Capital"
      ],
      "hidden": false
    }
  ],
  "2018-08-16": [
    {
      "headline": "New BOD member Carrie Teffner Appointed",
      "description": "<img src=\"/img/BOD-Carrie_Teffner.jfif\" class=\"headshot\" width=\"183\" height=\"275\" loading=\"lazy\">Carrie brings 30 years of financial leadership and experience and will join the audit committee. Carrie has served as Executive VP and CFO of Crocs since 2015. Prior to joining Crocs, she served as Executive VP and CFO at PetSmart and, before that, at Weber-Stephen Products. Prior to those roles, she served as Senior VP and CFO of Timberland",
      "source": [
        "https://news.gamestop.com/news-releases/news-release-details/gamestop-appoints-carrie-teffner-board-directors",
        "https://variety.com/2018/gaming/news/carrie-teffner-joins-gamestop-board-1202908050/"
      ],
      "icon": "fas fa-user-tie",
      "tags": [
        "board-of-directors",
        "appointment"
      ],
      "hidden": false
    }
  ],
  "2018-09-06": [
    {
      "headline": "GameStop Reports Q3 2018 Results",
      "description": "",
      "source": "https://news.gamestop.com/news-releases/news-release-details/gamestop-reports-second-quarter-fiscal-2018-results-and",
      "icon": "far fa-newspaper",
      "tags": "earnings",
      "hidden": false
    }
  ],
  "2018-11-14": [
    {
      "headline": "Melvin Capital Files 13F Revealing 13,257 $GME Put Contracts",
      "description": "Reporting up until 09/30/2018. The 13,257 put contracts were worth ~$20.2M",
      "source": "https://www.sec.gov/Archives/edgar/data/0001628110/000117266118002044/0001172661-18-002044-index.html",
      "icon": "fas fa-toilet",
      "tags": [
        "SEC",
        "filing",
        "Melvin-Capital"
      ],
      "hidden": false
    }
  ],
  "2018-11-21": [
    {
      "headline": "GameStop Announces Pending Sale of Subsidiary, Spring Mobile",
      "description": "GameStop exiting the mobile phone industry, selling Spring Mobile for $700M",
      "source": "https://www.gamesindustry.biz/articles/2016-08-02-gamestop-acquires-507-at-and-t-mobile-stores",
      "icon": "fas fa-mobile-alt",
      "tags": [
        "acquisitions",
        "Spring-Mobile"
      ],
      "hidden": false
    }
  ],
  "2018-11-29": [
    {
      "headline": "GameStop Reports Q3 2018 Results",
      "description": "",
      "source": "https://news.gamestop.com/news-releases/news-release-details/gamestop-reports-third-quarter-fiscal-2018-results-and-updates",
      "icon": "far fa-newspaper",
      "tags": "earnings",
      "hidden": false
    }
  ]
}